{
    "article_id": 24,
    "article_datetime": "9/12/2022 06:17:07",
    "article_label": "CENTER",
    "article_total_paragraphs": 55,
    "biased_by_these_sources": [
        23,
        49
    ],
    "biased_labels": {
        "LEFT": 1,
        "CENTER": 0,
        "RIGHT": 1
    },
    "is_biased": "Yes, to the LEFT",
    "earlier_articles": [
        {
            "article_id": 23,
            "article_label": "LEFT",
            "datetime": "9/12/2022 00:58:31",
            "total_paragraphs": 59,
            "total_reused_paragraphs": 54,
            "reused_ratio": 0.98,
            "is_biased_to": "Yes, to the LEFT. Percentage: 100.00%",
            "reused_paragraphs_label": {
                "LEFT": 54,
                "CENTER": 0,
                "RIGHT": 0
            },
            "reused_percentage": {
                "LEFT": 1.0,
                "CENTER": 0.0,
                "RIGHT": 0.0
            }
        },
        {
            "article_id": 27,
            "article_label": "CENTER",
            "datetime": "9/12/2022 02:06:10",
            "total_paragraphs": 19,
            "total_reused_paragraphs": 1,
            "reused_ratio": 0.02,
            "is_biased_to": "No",
            "reused_paragraphs_label": {
                "LEFT": 0,
                "CENTER": 1,
                "RIGHT": 0
            },
            "reused_percentage": {
                "LEFT": 0.0,
                "CENTER": 1.0,
                "RIGHT": 0.0
            }
        },
        {
            "article_id": 47,
            "article_label": "CENTER",
            "datetime": "8/12/2022 15:28:35",
            "total_paragraphs": 29,
            "total_reused_paragraphs": 0,
            "reused_ratio": 0.0,
            "is_biased_to": "No",
            "reused_paragraphs_label": {
                "LEFT": 0,
                "CENTER": 0,
                "RIGHT": 0
            },
            "reused_percentage": {
                "LEFT": 0,
                "CENTER": 0,
                "RIGHT": 0
            }
        },
        {
            "article_id": 49,
            "article_label": "RIGHT",
            "datetime": "8/12/2022 04:55:21",
            "total_paragraphs": 54,
            "total_reused_paragraphs": 49,
            "reused_ratio": 0.89,
            "is_biased_to": "Yes, to the RIGHT. Percentage: 100.00%",
            "reused_paragraphs_label": {
                "LEFT": 0,
                "CENTER": 0,
                "RIGHT": 49
            },
            "reused_percentage": {
                "LEFT": 0.0,
                "CENTER": 0.0,
                "RIGHT": 1.0
            }
        }
    ]
}