{
    "article_id": 5,
    "article_datetime": "9/12/2022 22:05",
    "article_label": "CENTER",
    "article_total_paragraphs": 21,
    "biased_by_these_sources": [
        2,
        3,
        4,
        6
    ],
    "biased_labels": {
        "LEFT": 4,
        "CENTER": 0,
        "RIGHT": 0
    },
    "is_biased": "Yes, to the LEFT",
    "earlier_articles": [
        {
            "article_id": 0,
            "article_label": "CENTER",
            "datetime": "9/12/2022 11:12:30",
            "total_paragraphs": 13,
            "total_reused_paragraphs": 7,
            "reused_ratio": 0.33,
            "is_biased_to": "No",
            "reused_paragraphs_label": {
                "LEFT": 6,
                "CENTER": 1,
                "RIGHT": 0
            },
            "reused_percentage": {
                "LEFT": 0.8571428571428571,
                "CENTER": 0.14285714285714285,
                "RIGHT": 0.0
            }
        },
        {
            "article_id": 1,
            "article_label": "CENTER",
            "datetime": "9/12/2022 01:32:12",
            "total_paragraphs": 2,
            "total_reused_paragraphs": 2,
            "reused_ratio": 0.1,
            "is_biased_to": "No",
            "reused_paragraphs_label": {
                "LEFT": 1,
                "CENTER": 1,
                "RIGHT": 0
            },
            "reused_percentage": {
                "LEFT": 0.5,
                "CENTER": 0.5,
                "RIGHT": 0.0
            }
        },
        {
            "article_id": 2,
            "article_label": "LEFT",
            "datetime": "9/12/2022 10:50:03",
            "total_paragraphs": 18,
            "total_reused_paragraphs": 18,
            "reused_ratio": 0.86,
            "is_biased_to": "Yes, to the LEFT. Percentage: 77.78%",
            "reused_paragraphs_label": {
                "LEFT": 14,
                "CENTER": 4,
                "RIGHT": 0
            },
            "reused_percentage": {
                "LEFT": 0.7777777777777778,
                "CENTER": 0.2222222222222222,
                "RIGHT": 0.0
            }
        },
        {
            "article_id": 3,
            "article_label": "RIGHT",
            "datetime": "9/12/2022 16:24:55",
            "total_paragraphs": 20,
            "total_reused_paragraphs": 18,
            "reused_ratio": 0.86,
            "is_biased_to": "Yes, to the LEFT. Percentage: 77.78%",
            "reused_paragraphs_label": {
                "LEFT": 14,
                "CENTER": 4,
                "RIGHT": 0
            },
            "reused_percentage": {
                "LEFT": 0.7777777777777778,
                "CENTER": 0.2222222222222222,
                "RIGHT": 0.0
            }
        },
        {
            "article_id": 4,
            "article_label": "LEFT",
            "datetime": "9/12/2022 14:04:39",
            "total_paragraphs": 18,
            "total_reused_paragraphs": 17,
            "reused_ratio": 0.81,
            "is_biased_to": "Yes, to the LEFT. Percentage: 76.47%",
            "reused_paragraphs_label": {
                "LEFT": 13,
                "CENTER": 4,
                "RIGHT": 0
            },
            "reused_percentage": {
                "LEFT": 0.7647058823529411,
                "CENTER": 0.23529411764705882,
                "RIGHT": 0.0
            }
        },
        {
            "article_id": 6,
            "article_label": "LEFT",
            "datetime": "9/12/2022 04:33:22",
            "total_paragraphs": 19,
            "total_reused_paragraphs": 17,
            "reused_ratio": 0.81,
            "is_biased_to": "Yes, to the LEFT. Percentage: 76.47%",
            "reused_paragraphs_label": {
                "LEFT": 13,
                "CENTER": 4,
                "RIGHT": 0
            },
            "reused_percentage": {
                "LEFT": 0.7647058823529411,
                "CENTER": 0.23529411764705882,
                "RIGHT": 0.0
            }
        }
    ]
}